dbsearch/__init__.py
dbsearch_anonymoosecoder-0.0.1.dist-info/LICENSE
dbsearch_anonymoosecoder-0.0.1.dist-info/METADATA
dbsearch_anonymoosecoder-0.0.1.dist-info/WHEEL
dbsearch_anonymoosecoder-0.0.1.dist-info/top_level.txt
dbsearch_anonymoosecoder-0.0.1.dist-info/RECORD
