Metadata-Version: 2.1
Name: dbsearch-anonymoosecoder
Version: 0.0.1
Summary: Database search engine
Home-page: https://github.com/pypa/sampleproject
Author: Dakyvion Dongen
Author-email: DakyvionD@hotmail.com
License: UNKNOWN
Platform: UNKNOWN
Classifier: Programming Language :: Python :: 3
Classifier: License :: OSI Approved :: MIT License
Classifier: Operating System :: OS Independent
Requires-Python: >=3.6
